{
  "suppliers": [
    {
      "componentType": "Split System Air Conditioners",
      "suppliers": [
        {
          "manufacturer": "Samsung HVAC",
          "model": "AC Series",
          "isBasisOfDesign": true,
          "isListedAlternate": false,
          "representativeInfo": {
            "name": "",
            "company": "",
            "contact": ""
          },
          "costDifference": "",
          "compatibilityNotes": ""
        },
        {
          "manufacturer": "Daikin",
          "model": "FTXS Series",
          "isBasisOfDesign": false,
          "isListedAlternate": true,
          "representativeInfo": {
            "name": "Norman S. Wright Climatec",
            "company": "Norman S. Wright Climatec Mechanical Equipment",
            "contact": "(714) 632-9800"
          },
          "costDifference": "-5%",
          "compatibilityNotes": "Compatible with existing ductwork, may require adapters for refrigerant lines"
        },
        {
          "manufacturer": "Mitsubishi Electric",
          "model": "MSZ-FS Series",
          "isBasisOfDesign": false,
          "isListedAlternate": true,
          "representativeInfo": {
            "name": "CFM Equipment Distributors",
            "company": "CFM Equipment Distributors",
            "contact": "(916) 447-7022"
          },
          "costDifference": "+8%",
          "compatibilityNotes": "Premium option with improved energy efficiency ratings"
        },
        {
          "manufacturer": "LG",
          "model": "Art Cool Series",
          "isBasisOfDesign": false,
          "isListedAlternate": false,
          "representativeInfo": {
            "name": "Johnstone Supply",
            "company": "Johnstone Supply",
            "contact": ""
          },
          "costDifference": "-3%",
          "compatibilityNotes": "SUGGESTED ALTERNATIVE: Compatible with existing systems, good energy efficiency and reliability ratings"
        },
        {
          "manufacturer": "Fujitsu",
          "model": "Halcyon Series",
          "isBasisOfDesign": false,
          "isListedAlternate": false,
          "representativeInfo": {
            "name": "United Refrigeration",
            "company": "United Refrigeration",
            "contact": ""
          },
          "costDifference": "-2%",
          "compatibilityNotes": "SUGGESTED ALTERNATIVE: Highly efficient mini-splits with quiet operation and similar installation requirements"
        }
      ]
    },
    {
      "componentType": "Packaged Rooftop Air-Conditioning Units",
      "suppliers": [
        {
          "manufacturer": "York",
          "model": "PACKAGED DX Series",
          "isBasisOfDesign": true,
          "isListedAlternate": false,
          "representativeInfo": {
            "name": "",
            "company": "",
            "contact": ""
          },
          "costDifference": "",
          "compatibilityNotes": ""
        },
        {
          "manufacturer": "Carrier",
          "model": "WeatherMaker Series",
          "isBasisOfDesign": false,
          "isListedAlternate": true,
          "representativeInfo": {
            "name": "Russell Sigler Inc.",
            "company": "Russell Sigler Inc.",
            "contact": "sales@siglers.com"
          },
          "costDifference": "+3%",
          "compatibilityNotes": "Similar footprint, would require minimal roof curb modifications"
        },
        {
          "manufacturer": "Trane",
          "model": "Precedent Series",
          "isBasisOfDesign": false,
          "isListedAlternate": true,
          "representativeInfo": {
            "name": "US Air Conditioning Distributors",
            "company": "US Air Conditioning Distributors",
            "contact": "info@us-ac.com"
          },
          "costDifference": "+6%",
          "compatibilityNotes": "Higher efficiency option with robust control package"
        },
        {
          "manufacturer": "Lennox",
          "model": "Energence Series",
          "isBasisOfDesign": false,
          "isListedAlternate": false,
          "representativeInfo": {
            "name": "Lennox Industries",
            "company": "Lennox Industries",
            "contact": ""
          },
          "costDifference": "-2%",
          "compatibilityNotes": "SUGGESTED ALTERNATIVE: High-efficiency units with good serviceability and competitive pricing"
        },
        {
          "manufacturer": "Daikin",
          "model": "Rebel Series",
          "isBasisOfDesign": false,
          "isListedAlternate": false,
          "representativeInfo": {
            "name": "Daikin Applied",
            "company": "Daikin Applied",
            "contact": ""
          },
          "costDifference": "+7%",
          "compatibilityNotes": "SUGGESTED ALTERNATIVE: Premium efficiency with variable speed technology and advanced controls"
        }
      ]
    },
    {
      "componentType": "Dedicated Outdoor-Air Units",
      "suppliers": [
        {
          "manufacturer": "iAire",
          "model": "PHC Series",
          "isBasisOfDesign": true,
          "isListedAlternate": false,
          "representativeInfo": {
            "name": "",
            "company": "",
            "contact": ""
          },
          "costDifference": "",
          "compatibilityNotes": ""
        },
        {
          "manufacturer": "Greenheck",
          "model": "DGK Series",
          "isBasisOfDesign": false,
          "isListedAlternate": false,
          "representativeInfo": {
            "name": "Greenheck Representatives",
            "company": "Greenheck",
            "contact": ""
          },
          "costDifference": "-3%",
          "compatibilityNotes": "SUGGESTED ALTERNATIVE: Comparable performance with good energy recovery efficiency and robust construction"
        },
        {
          "manufacturer": "Aaon",
          "model": "M2 Series",
          "isBasisOfDesign": false,
          "isListedAlternate": false,
          "representativeInfo": {
            "name": "Aaon Representatives",
            "company": "Aaon",
            "contact": ""
          },
          "costDifference": "+5%",
          "compatibilityNotes": "SUGGESTED ALTERNATIVE: Premium quality with excellent energy recovery effectiveness and advanced control options"
        },
        {
          "manufacturer": "Trane",
          "model": "Performance Climate Changer",
          "isBasisOfDesign": false,
          "isListedAlternate": false,
          "representativeInfo": {
            "name": "Trane Technologies",
            "company": "Trane Technologies",
            "contact": ""
          },
          "costDifference": "+7%",
          "compatibilityNotes": "SUGGESTED ALTERNATIVE: High-end unit with custom configuration options and integration with Trane building controls"
        }
      ]
    },
    {
      "componentType": "HVAC Fans",
      "suppliers": [
        {
          "manufacturer": "Greenheck",
          "model": "CUE/FJI Series",
          "isBasisOfDesign": true,
          "isListedAlternate": false,
          "representativeInfo": {
            "name": "",
            "company": "",
            "contact": ""
          },
          "costDifference": "",
          "compatibilityNotes": ""
        },
        {
          "manufacturer": "Twin City Fan",
          "model": "BSI/BCE Series",
          "isBasisOfDesign": false,
          "isListedAlternate": false,
          "representativeInfo": {
            "name": "Twin City Fan Representatives",
            "company": "Twin City Fan",
            "contact": ""
          },
          "costDifference": "-7%",
          "compatibilityNotes": "SUGGESTED ALTERNATIVE: Cost-effective alternative with comparable performance specifications"
        },
        {
          "manufacturer": "Loren Cook",
          "model": "Gemini/Acme Series",
          "isBasisOfDesign": false,
          "isListedAlternate": false,
          "representativeInfo": {
            "name": "Loren Cook Representatives",
            "company": "Loren Cook Company",
            "contact": ""
          },
          "costDifference": "-5%",
          "compatibilityNotes": "SUGGESTED ALTERNATIVE: Direct replacement options with similar dimensions and capacities"
        },
        {
          "manufacturer": "PennBarry",
          "model": "Zephyr/Domex Series",
          "isBasisOfDesign": false,
          "isListedAlternate": false,
          "representativeInfo": {
            "name": "PennBarry Representatives",
            "company": "PennBarry",
            "contact": ""
          },
          "costDifference": "-10%",
          "compatibilityNotes": "SUGGESTED ALTERNATIVE: Economy option with acceptable performance metrics for most applications"
        }
      ]
    },
    {
      "componentType": "Condensing Boilers",
      "suppliers": [
        {
          "manufacturer": "Raypak",
          "model": "H7 Series",
          "isBasisOfDesign": true,
          "isListedAlternate": false,
          "representativeInfo": {
            "name": "",
            "company": "",
            "contact": ""
          },
          "costDifference": "",
          "compatibilityNotes": ""
        },
        {
          "manufacturer": "Lochinvar",
          "model": "KNIGHT Series",
          "isBasisOfDesign": false,
          "isListedAlternate": true,
          "representativeInfo": {
            "name": "DB Sales & Service",
            "company": "DB Sales & Service",
            "contact": "(714) 897-1036"
          },
          "costDifference": "+4%",
          "compatibilityNotes": "Higher efficiency with built-in redundancy features"
        },
        {
          "manufacturer": "Aerco",
          "model": "Benchmark Series",
          "isBasisOfDesign": false,
          "isListedAlternate": true,
          "representativeInfo": {
            "name": "California Hot Water Supply",
            "company": "California Hot Water Supply",
            "contact": "(888) 249-7244"
          },
          "costDifference": "+10%",
          "compatibilityNotes": "Premium option with advanced modulation capabilities"
        },
        {
          "manufacturer": "Cleaver-Brooks",
          "model": "ClearFire Series",
          "isBasisOfDesign": false,
          "isListedAlternate": false,
          "representativeInfo": {
            "name": "R.F. MacDonald Co.",
            "company": "R.F. MacDonald Co.",
            "contact": ""
          },
          "costDifference": "+2%",
          "compatibilityNotes": "SUGGESTED ALTERNATIVE: High-quality boilers with excellent turndown ratio and efficiency"
        },
        {
          "manufacturer": "Viessmann",
          "model": "Vitocrossal Series",
          "isBasisOfDesign": false,
          "isListedAlternate": false,
          "representativeInfo": {
            "name": "Ferguson",
            "company": "Ferguson",
            "contact": ""
          },
          "costDifference": "+12%",
          "compatibilityNotes": "SUGGESTED ALTERNATIVE: German-engineered premium boilers with industry-leading efficiency and longevity"
        }
      ]
    }
  ]
}
