{
  "suppliers": [
    {
      "componentType": "Dedicated Outdoor-Air Units",
      "suppliers": [
        {
          "manufacturer": "AAON",
          "model": "RQA-002",
          "isBasisOfDesign": true,
          "isListedAlternate": false,
          "representativeInfo": {
            "name": "Gil Bar Inc",
            "company": "Gil Bar Inc",
            "contact": "Matt Neumann, mneumann@gil-bar.com"
          },
          "costDifference": "",
          "compatibilityNotes": "Basis of Design"
        },
        {
          "manufacturer": "Daikin",
          "model": "Rebel",
          "isBasisOfDesign": false,
          "isListedAlternate": true,
          "representativeInfo": {
            "name": "",
            "company": "Daikin Representative",
            "contact": ""
          },
          "costDifference": "+5-10%",
          "compatibilityNotes": "Compatible alternative with similar performance specifications"
        },
        {
          "manufacturer": "Greenheck",
          "model": "RV Series",
          "isBasisOfDesign": false,
          "isListedAlternate": false,
          "representativeInfo": {
            "name": "",
            "company": "Greenheck Representative",
            "contact": ""
          },
          "costDifference": "-3%",
          "compatibilityNotes": "SUGGESTED ALTERNATIVE: Energy recovery capability and modular design makes this a good alternative for ventilation requirements"
        },
        {
          "manufacturer": "Valent",
          "model": "VR Series",
          "isBasisOfDesign": false,
          "isListedAlternate": false,
          "representativeInfo": {
            "name": "",
            "company": "Valent Representative",
            "contact": ""
          },
          "costDifference": "-2%",
          "compatibilityNotes": "SUGGESTED ALTERNATIVE: High-efficiency energy recovery units with similar performance characteristics to AAON"
        }
      ]
    },
    {
      "componentType": "Split System Air Conditioners",
      "suppliers": [
        {
          "manufacturer": "Mitsubishi Electric (Including Trane Products)",
          "model": "SUZ-KA12NAHZ",
          "isBasisOfDesign": true,
          "isListedAlternate": false,
          "representativeInfo": {
            "name": "SRS Enterprises Inc.",
            "company": "SRS Enterprises Inc.",
            "contact": "732-787-5062, www.srs-enterprises.com"
          },
          "costDifference": "",
          "compatibilityNotes": "Basis of Design"
        },
        {
          "manufacturer": "Daikin",
          "model": "RXS12LVJU",
          "isBasisOfDesign": false,
          "isListedAlternate": true,
          "representativeInfo": {
            "name": "",
            "company": "Daikin Representative",
            "contact": ""
          },
          "costDifference": "-3%",
          "compatibilityNotes": "Compatible alternative with similar performance specifications"
        },
        {
          "manufacturer": "Carrier",
          "model": "38MGRQ12",
          "isBasisOfDesign": false,
          "isListedAlternate": false,
          "representativeInfo": {
            "name": "",
            "company": "Carrier Representative",
            "contact": ""
          },
          "costDifference": "+2%",
          "compatibilityNotes": "SUGGESTED ALTERNATIVE: High-efficiency heat pump option with good reliability and similar footprint to specified unit"
        },
        {
          "manufacturer": "LG",
          "model": "LAU120HYV",
          "isBasisOfDesign": false,
          "isListedAlternate": false,
          "representativeInfo": {
            "name": "",
            "company": "LG Representative",
            "contact": ""
          },
          "costDifference": "-5%",
          "compatibilityNotes": "SUGGESTED ALTERNATIVE: Cost-effective alternative with competitive efficiency ratings and increasingly popular in commercial applications"
        }
      ]
    },
    {
      "componentType": "Water-Source Heat Pumps",
      "suppliers": [
        {
          "manufacturer": "Mitsubishi Electric (Including Trane Products)",
          "model": "NTXMSM60A182BA",
          "isBasisOfDesign": true,
          "isListedAlternate": false,
          "representativeInfo": {
            "name": "SRS Enterprises Inc.",
            "company": "SRS Enterprises Inc.",
            "contact": "732-787-5062, www.srs-enterprises.com"
          },
          "costDifference": "",
          "compatibilityNotes": "Basis of Design"
        },
        {
          "manufacturer": "ClimateMaster",
          "model": "TMW060",
          "isBasisOfDesign": false,
          "isListedAlternate": true,
          "representativeInfo": {
            "name": "",
            "company": "ClimateMaster Representative",
            "contact": ""
          },
          "costDifference": "-5%",
          "compatibilityNotes": "Compatible alternative with similar performance specifications"
        },
        {
          "manufacturer": "WaterFurnace",
          "model": "NSW060",
          "isBasisOfDesign": false,
          "isListedAlternate": false,
          "representativeInfo": {
            "name": "",
            "company": "WaterFurnace Representative",
            "contact": ""
          },
          "costDifference": "-4%",
          "compatibilityNotes": "SUGGESTED ALTERNATIVE: High efficiency water-source heat pump with good track record of reliability"
        },
        {
          "manufacturer": "Florida Heat Pump",
          "model": "EC Series",
          "isBasisOfDesign": false,
          "isListedAlternate": false,
          "representativeInfo": {
            "name": "",
            "company": "Florida Heat Pump Representative",
            "contact": ""
          },
          "costDifference": "-7%",
          "compatibilityNotes": "SUGGESTED ALTERNATIVE: Cost-effective alternative with good performance and standard components that simplify maintenance"
        }
      ]
    },
    {
      "componentType": "Fan Coil Units",
      "suppliers": [
        {
          "manufacturer": "Mitsubishi Electric (Including Trane Products)",
          "model": "SLZ-KF15NA1",
          "isBasisOfDesign": true,
          "isListedAlternate": false,
          "representativeInfo": {
            "name": "SRS Enterprises Inc.",
            "company": "SRS Enterprises Inc.",
            "contact": "732-787-5062, www.srs-enterprises.com"
          },
          "costDifference": "",
          "compatibilityNotes": "Basis of Design"
        },
        {
          "manufacturer": "Daikin",
          "model": "FXFQ15TVJU",
          "isBasisOfDesign": false,
          "isListedAlternate": true,
          "representativeInfo": {
            "name": "",
            "company": "Daikin Representative",
            "contact": ""
          },
          "costDifference": "+2%",
          "compatibilityNotes": "Compatible alternative with similar performance specifications"
        },
        {
          "manufacturer": "First Co",
          "model": "VFC Series",
          "isBasisOfDesign": false,
          "isListedAlternate": false,
          "representativeInfo": {
            "name": "",
            "company": "First Co Representative",
            "contact": ""
          },
          "costDifference": "-8%",
          "compatibilityNotes": "SUGGESTED ALTERNATIVE: Cost-effective vertical fan coil option with similar capacity and compatible dimensions"
        },
        {
          "manufacturer": "IEC",
          "model": "FCV Series",
          "isBasisOfDesign": false,
          "isListedAlternate": false,
          "representativeInfo": {
            "name": "",
            "company": "IEC Representative",
            "contact": ""
          },
          "costDifference": "-6%",
          "compatibilityNotes": "SUGGESTED ALTERNATIVE: Reliable alternative with competitive efficiency and standard components for easy maintenance"
        }
      ]
    },
    {
      "componentType": "Variable Refrigerant Flow Systems",
      "suppliers": [
        {
          "manufacturer": "Mitsubishi Electric (Including Trane Products)",
          "model": "TPLA0A0241EA80A",
          "isBasisOfDesign": true,
          "isListedAlternate": false,
          "representativeInfo": {
            "name": "SRS Enterprises Inc.",
            "company": "SRS Enterprises Inc.",
            "contact": "732-787-5062, www.srs-enterprises.com"
          },
          "costDifference": "",
          "compatibilityNotes": "Basis of Design"
        },
        {
          "manufacturer": "LG",
          "model": "ARNU24GSCR4",
          "isBasisOfDesign": false,
          "isListedAlternate": true,
          "representativeInfo": {
            "name": "",
            "company": "LG Representative",
            "contact": ""
          },
          "costDifference": "-4%",
          "compatibilityNotes": "Compatible alternative with similar performance specifications"
        },
        {
          "manufacturer": "Samsung",
          "model": "AM024FNNDCH",
          "isBasisOfDesign": false,
          "isListedAlternate": false,
          "representativeInfo": {
            "name": "",
            "company": "Samsung Representative",
            "contact": ""
          },
          "costDifference": "-6%",
          "compatibilityNotes": "SUGGESTED ALTERNATIVE: Cost-effective VRF system with good efficiency and reliability"
        },
        {
          "manufacturer": "Daikin",
          "model": "FXMQ24PBVJU",
          "isBasisOfDesign": false,
          "isListedAlternate": false,
          "representativeInfo": {
            "name": "",
            "company": "Daikin Representative",
            "contact": ""
          },
          "costDifference": "+1%",
          "compatibilityNotes": "SUGGESTED ALTERNATIVE: High-quality alternative with excellent distributor support and parts availability"
        }
      ]
    },
    {
      "componentType": "Packaged Rooftop Air-Conditioning Units",
      "suppliers": [
        {
          "manufacturer": "Trane",
          "model": "WHK060A3",
          "isBasisOfDesign": true,
          "isListedAlternate": false,
          "representativeInfo": {
            "name": "Trane New Jersey",
            "company": "Trane Commercial Sales Office",
            "contact": "973-244-7434, www.trane.com/commercial"
          },
          "costDifference": "",
          "compatibilityNotes": "Basis of Design"
        },
        {
          "manufacturer": "Carrier",
          "model": "48TC06",
          "isBasisOfDesign": false,
          "isListedAlternate": true,
          "representativeInfo": {
            "name": "",
            "company": "Carrier Representative",
            "contact": ""
          },
          "costDifference": "+3%",
          "compatibilityNotes": "Compatible alternative with similar performance specifications"
        },
        {
          "manufacturer": "York",
          "model": "ZF060",
          "isBasisOfDesign": false,
          "isListedAlternate": false,
          "representativeInfo": {
            "name": "",
            "company": "York Representative",
            "contact": ""
          },
          "costDifference": "-2%",
          "compatibilityNotes": "SUGGESTED ALTERNATIVE: Cost-effective option with similar footprint and performance to specified unit"
        },
        {
          "manufacturer": "Lennox",
          "model": "LCH060H4",
          "isBasisOfDesign": false,
          "isListedAlternate": false,
          "representativeInfo": {
            "name": "",
            "company": "Lennox Representative",
            "contact": ""
          },
          "costDifference": "-4%",
          "compatibilityNotes": "SUGGESTED ALTERNATIVE: High-efficiency option with competitive pricing and good reliability"
        }
      ]
    },
    {
      "componentType": "HVAC Fans",
      "suppliers": [
        {
          "manufacturer": "Greenheck",
          "model": "GB-140",
          "isBasisOfDesign": true,
          "isListedAlternate": false,
          "representativeInfo": {
            "name": "ADE Systems Inc.",
            "company": "ADE Systems Inc.",
            "contact": "tbrady@adehvac.com"
          },
          "costDifference": "",
          "compatibilityNotes": "Basis of Design"
        },
        {
          "manufacturer": "Loren Cook",
          "model": "30 XLW S",
          "isBasisOfDesign": true,
          "isListedAlternate": false,
          "representativeInfo": {
            "name": "Mechanical Technologies, LLC",
            "company": "Mechanical Technologies, LLC",
            "contact": "973-616-3800, richf@mthvac.com"
          },
          "costDifference": "",
          "compatibilityNotes": "Basis of Design for specific fan applications"
        },
        {
          "manufacturer": "Twin City Fan",
          "model": "BCRD",
          "isBasisOfDesign": false,
          "isListedAlternate": true,
          "representativeInfo": {
            "name": "",
            "company": "Twin City Fan Representative",
            "contact": ""
          },
          "costDifference": "-2%",
          "compatibilityNotes": "Compatible alternative with similar performance specifications"
        },
        {
          "manufacturer": "PennBarry",
          "model": "Dynamo Series",
          "isBasisOfDesign": false,
          "isListedAlternate": false,
          "representativeInfo": {
            "name": "",
            "company": "PennBarry Representative",
            "contact": ""
          },
          "costDifference": "-5%",
          "compatibilityNotes": "SUGGESTED ALTERNATIVE: Cost-effective centrifugal fans with similar performance characteristics"
        },
        {
          "manufacturer": "Fantech",
          "model": "FG Series",
          "isBasisOfDesign": false,
          "isListedAlternate": false,
          "representativeInfo": {
            "name": "",
            "company": "Fantech Representative",
            "contact": ""
          },
          "costDifference": "-7%",
          "compatibilityNotes": "SUGGESTED ALTERNATIVE: Economical inline fans suitable for many exhaust applications with good reliability"
        }
      ]
    }
  ]
}
